{
  "mode": "topological-gw",
  "graph_prior": "3d-local",
  "degree": 8,
  "temperature": 0.12,
  "anneal_start_temperature": 0.9,
  "critical_temperature": 0.55,
  "burn_in_sweeps": 100,
  "measurement_sweeps": 20,
  "sample_interval": 2,
  "edge_swap_attempts_per_sweep": 256,
  "field_updates_per_sweep": 1024,
  "amplitude_step": 0.18,
  "phase_step": 0.35,
  "gradient_coupling": 1.0,
  "symmetry_scale": 1.0,
  "self_coupling": 1.0,
  "defect_amplitude_floor": 0.15,
  "calibration": {
    "enabled": true,
    "transition_temperature_gev": 100.0,
    "beta_over_hstar": 100.0,
    "simulation_to_source_frequency": 1.0,
    "stress_to_energy_fraction": 1.0,
    "reference_temperature_gev": 100.0,
    "frequency_prefactor_hz": 1.65e-05,
    "radiation_density_h2": 4e-05
  },
  "points": [
    {
      "sites": 1024,
      "seed": 7,
      "graph_prior": "3d-local",
      "degree": 8,
      "edge_count": 4427,
      "plaquette_count": 122,
      "samples_collected": 61,
      "transition_sweep": null,
      "transition_temperature": null,
      "final_mean_amplitude": 0.07534492872057325,
      "final_coherence": 0.037899355281352264,
      "final_defect_density": 0.0,
      "peak_defect_density": 1.0,
      "integrated_stress_power": 1.1383768502632282e-07,
      "peak_frequency": 0.00819672131147541,
      "peak_spectral_power": 7.970200075576313e-06,
      "calibrated_prediction": {
        "present_day_peak_frequency_hz": 1.3524590163934428e-05,
        "present_day_peak_frequency_uhz": 13.524590163934429,
        "present_day_peak_frequency_nhz": 13524.590163934428,
        "omega_gw_h2": 4.553507401052913e-12,
        "notes": [
          "Calibration is an explicit post-processing assumption layer.",
          "f_peak^sim is defined in inverse sweeps, not in physical source time.",
          "Omega_GW h^2 is inferred from a user-specified stress-to-energy transfer factor."
        ]
      },
      "samples": [
        {
          "sweep": 0,
          "temperature": 0.9,
          "mean_amplitude": 0.06224072066368231,
          "coherence": 0.027152878857570017,
          "order_parameter_abs": 0.0016900147481888207,
          "order_parameter_phase": -0.6629686253469506,
          "defect_density": 0.0,
          "mean_winding_abs": 0.0,
          "gradient_energy": 43.65101405277577,
          "potential_energy": 1.7827442979992385,
          "total_energy": 45.43375835077501,
          "stress_power": 9.081767817453915e-14
        },
        {
          "sweep": 2,
          "temperature": 0.8844000000000001,
          "mean_amplitude": 0.12410974131650246,
          "coherence": 0.0168902710824051,
          "order_parameter_abs": 0.0020962471748028986,
          "order_parameter_phase": -1.7124869281762731,
          "defect_density": 0.203125,
          "mean_winding_abs": 0.203125,
          "gradient_energy": 219.2453306483071,
          "potential_energy": 10.214857661101409,
          "total_energy": 229.4601883094085,
          "stress_power": 0.0009395950637742909
        },
        {
          "sweep": 4,
          "temperature": 0.8688,
          "mean_amplitude": 0.14758720269183684,
          "coherence": 0.02403714670497569,
          "order_parameter_abs": 0.003547575242880665,
          "order_parameter_phase": -0.8872912682611461,
          "defect_density": 0.1958762886597938,
          "mean_winding_abs": 0.1958762886597938,
          "gradient_energy": 290.9347428154903,
          "potential_energy": 13.853608715081844,
          "total_energy": 304.7883515305722,
          "stress_power": 0.001414509447779933
        },
        {
          "sweep": 6,
          "temperature": 0.8532000000000001,
          "mean_amplitude": 0.1584849429509835,
          "coherence": 0.018136289569744873,
          "order_parameter_abs": 0.0028743288178035334,
          "order_parameter_phase": -1.663028138480541,
          "defect_density": 0.2222222222222222,
          "mean_winding_abs": 0.2222222222222222,
          "gradient_energy": 339.5190620357966,
          "potential_energy": 15.982277762753931,
          "total_energy": 355.50133979855053,
          "stress_power": 0.0023326003469300066
        },
        {
          "sweep": 8,
          "temperature": 0.8376,
          "mean_amplitude": 0.16456817221035158,
          "coherence": 0.015753096148274193,
          "order_parameter_abs": 0.0025924582397754137,
          "order_parameter_phase": -0.23682136544170834,
          "defect_density": 0.05434782608695652,
          "mean_winding_abs": 0.05434782608695652,
          "gradient_energy": 353.29024531616244,
          "potential_energy": 15.752161851294309,
          "total_energy": 369.04240716745676,
          "stress_power": 0.0005293113424973014
        },
        {
          "sweep": 10,
          "temperature": 0.8220000000000001,
          "mean_amplitude": 0.1645018934326027,
          "coherence": 0.038880822747638724,
          "order_parameter_abs": 0.006395968960203981,
          "order_parameter_phase": -0.6130285871496463,
          "defect_density": 0.13333333333333333,
          "mean_winding_abs": 0.13333333333333333,
          "gradient_energy": 332.1606134096502,
          "potential_energy": 14.798145395271115,
          "total_energy": 346.9587588049213,
          "stress_power": 0.0011059757505555898
        },
        {
          "sweep": 12,
          "temperature": 0.8064,
          "mean_amplitude": 0.17077651400147104,
          "coherence": 0.013741708938932265,
          "order_parameter_abs": 0.0023467611490137056,
          "order_parameter_phase": -1.20288499001713,
          "defect_density": 0.15,
          "mean_winding_abs": 0.15,
          "gradient_energy": 355.18208707736477,
          "potential_energy": 15.191065999775935,
          "total_energy": 370.3731530771407,
          "stress_power": 0.001380649756773496
        },
        {
          "sweep": 14,
          "temperature": 0.7908,
          "mean_amplitude": 0.17197857568001895,
          "coherence": 0.019102976758809564,
          "order_parameter_abs": 0.003285302734228574,
          "order_parameter_phase": -0.8412589842475808,
          "defect_density": 0.10256410256410256,
          "mean_winding_abs": 0.10256410256410256,
          "gradient_energy": 348.57377882523497,
          "potential_energy": 15.216342406744996,
          "total_energy": 363.79012123198,
          "stress_power": 0.0008715019614877779
        },
        {
          "sweep": 16,
          "temperature": 0.7752,
          "mean_amplitude": 0.17231521802028635,
          "coherence": 0.009199799949958216,
          "order_parameter_abs": 0.0015852655341200696,
          "order_parameter_phase": 0.165193751790169,
          "defect_density": 0.038461538461538464,
          "mean_winding_abs": 0.038461538461538464,
          "gradient_energy": 349.0775531936369,
          "potential_energy": 15.025185811875145,
          "total_energy": 364.10273900551203,
          "stress_power": 0.0003382125637051632
        },
        {
          "sweep": 18,
          "temperature": 0.7596,
          "mean_amplitude": 0.17140552205513687,
          "coherence": 0.02417121545972255,
          "order_parameter_abs": 0.004143079804580939,
          "order_parameter_phase": -3.124026938116743,
          "defect_density": 0.17391304347826086,
          "mean_winding_abs": 0.17391304347826086,
          "gradient_energy": 350.1626199778746,
          "potential_energy": 14.222691778040996,
          "total_energy": 364.3853117559156,
          "stress_power": 0.001655527603977568
        },
        {
          "sweep": 20,
          "temperature": 0.744,
          "mean_amplitude": 0.1719796388872728,
          "coherence": 0.023579058042871526,
          "order_parameter_abs": 0.0040551178875150905,
          "order_parameter_phase": 2.1997129876982786,
          "defect_density": 0.11764705882352941,
          "mean_winding_abs": 0.11764705882352941,
          "gradient_energy": 354.1315841375355,
          "potential_energy": 13.761890892372996,
          "total_energy": 367.89347502990853,
          "stress_power": 0.0011499221865568857
        },
        {
          "sweep": 22,
          "temperature": 0.7284,
          "mean_amplitude": 0.17046369504227665,
          "coherence": 0.028677740345104424,
          "order_parameter_abs": 0.0048885135846894745,
          "order_parameter_phase": -2.9518097026823265,
          "defect_density": 0.1875,
          "mean_winding_abs": 0.1875,
          "gradient_energy": 346.2355328500557,
          "potential_energy": 13.87547348542665,
          "total_energy": 360.11100633548233,
          "stress_power": 0.0019084501135733566
        },
        {
          "sweep": 24,
          "temperature": 0.7128,
          "mean_amplitude": 0.17146073043692334,
          "coherence": 0.03472040472015649,
          "order_parameter_abs": 0.0059531859543836335,
          "order_parameter_phase": 2.796384930030793,
          "defect_density": 0.16666666666666666,
          "mean_winding_abs": 0.16666666666666666,
          "gradient_energy": 348.69464051490286,
          "potential_energy": 12.418914187866681,
          "total_energy": 361.11355470276953,
          "stress_power": 0.001687910094168364
        },
        {
          "sweep": 26,
          "temperature": 0.6972,
          "mean_amplitude": 0.175027385018042,
          "coherence": 0.0390453469445671,
          "order_parameter_abs": 0.006834004972829775,
          "order_parameter_phase": 2.576184562298327,
          "defect_density": 0.05263157894736842,
          "mean_winding_abs": 0.05263157894736842,
          "gradient_energy": 356.9266035611437,
          "potential_energy": 11.727130116979836,
          "total_energy": 368.6537336781235,
          "stress_power": 0.0005215910861959048
        },
        {
          "sweep": 28,
          "temperature": 0.6816,
          "mean_amplitude": 0.1709981700323166,
          "coherence": 0.039425733617539746,
          "order_parameter_abs": 0.006741728300780883,
          "order_parameter_phase": 2.329076008115219,
          "defect_density": 0.16666666666666666,
          "mean_winding_abs": 0.16666666666666666,
          "gradient_energy": 351.92210994037964,
          "potential_energy": 10.651330944336712,
          "total_energy": 362.5734408847164,
          "stress_power": 0.0016004989699039478
        },
        {
          "sweep": 30,
          "temperature": 0.666,
          "mean_amplitude": 0.17169667615471318,
          "coherence": 0.04791924521517061,
          "order_parameter_abs": 0.008227575127287437,
          "order_parameter_phase": 2.491998092445105,
          "defect_density": 0.2222222222222222,
          "mean_winding_abs": 0.2222222222222222,
          "gradient_energy": 359.6910783601875,
          "potential_energy": 9.657570486000614,
          "total_energy": 369.3486488461881,
          "stress_power": 0.002099056717304044
        },
        {
          "sweep": 32,
          "temperature": 0.6504,
          "mean_amplitude": 0.176095356917725,
          "coherence": 0.028806338112745685,
          "order_parameter_abs": 0.005072662391456616,
          "order_parameter_phase": 2.6656517677942912,
          "defect_density": 0.13333333333333333,
          "mean_winding_abs": 0.13333333333333333,
          "gradient_energy": 365.5770794227125,
          "potential_energy": 8.957792265489584,
          "total_energy": 374.53487168820203,
          "stress_power": 0.0014422989130236296
        },
        {
          "sweep": 34,
          "temperature": 0.6348,
          "mean_amplitude": 0.17653083441812545,
          "coherence": 0.026981300484535956,
          "order_parameter_abs": 0.0047630314882213046,
          "order_parameter_phase": 2.394095161123382,
          "defect_density": 0.15789473684210525,
          "mean_winding_abs": 0.15789473684210525,
          "gradient_energy": 357.29458585800137,
          "potential_energy": 7.784355829590599,
          "total_energy": 365.07894168759196,
          "stress_power": 0.0014178467735859344
        },
        {
          "sweep": 36,
          "temperature": 0.6192,
          "mean_amplitude": 0.1599560950272792,
          "coherence": 0.054455052008568365,
          "order_parameter_abs": 0.008710417473797992,
          "order_parameter_phase": 2.536195451396969,
          "defect_density": 0.16666666666666666,
          "mean_winding_abs": 0.16666666666666666,
          "gradient_energy": 313.4212164647298,
          "potential_energy": 6.12467967362884,
          "total_energy": 319.54589613835867,
          "stress_power": 0.0013008575478068653
        },
        {
          "sweep": 38,
          "temperature": 0.6036,
          "mean_amplitude": 0.15892188916393787,
          "coherence": 0.008881620621729903,
          "order_parameter_abs": 0.0014114839280427048,
          "order_parameter_phase": 2.6271870694392447,
          "defect_density": 0.14285714285714285,
          "mean_winding_abs": 0.14285714285714285,
          "gradient_energy": 299.63625979387973,
          "potential_energy": 5.918054670736674,
          "total_energy": 305.5543144646164,
          "stress_power": 0.0011265052417246
        },
        {
          "sweep": 40,
          "temperature": 0.588,
          "mean_amplitude": 0.1601720008228922,
          "coherence": 0.019250020495862507,
          "order_parameter_abs": 0.0030833142987039814,
          "order_parameter_phase": -2.7753452332056363,
          "defect_density": 0.1,
          "mean_winding_abs": 0.1,
          "gradient_energy": 301.89189243911335,
          "potential_energy": 5.051549096797529,
          "total_energy": 306.9434415359109,
          "stress_power": 0.0007532241031549212
        },
        {
          "sweep": 42,
          "temperature": 0.5724,
          "mean_amplitude": 0.1583003132930408,
          "coherence": 0.012402920939399147,
          "order_parameter_abs": 0.001963386270455701,
          "order_parameter_phase": 0.09851404704673082,
          "defect_density": 0.14285714285714285,
          "mean_winding_abs": 0.14285714285714285,
          "gradient_energy": 290.5074473916791,
          "potential_energy": 3.8081469126870804,
          "total_energy": 294.3155943043662,
          "stress_power": 0.0009956245289267215
        },
        {
          "sweep": 44,
          "temperature": 0.5568,
          "mean_amplitude": 0.1556702074611801,
          "coherence": 0.03188770718718818,
          "order_parameter_abs": 0.004963965993290948,
          "order_parameter_phase": -0.3918462251453601,
          "defect_density": 0.16666666666666666,
          "mean_winding_abs": 0.16666666666666666,
          "gradient_energy": 285.05498445163875,
          "potential_energy": 3.0660143612602595,
          "total_energy": 288.120998812899,
          "stress_power": 0.0010835785845561567
        },
        {
          "sweep": 46,
          "temperature": 0.5412,
          "mean_amplitude": 0.15854011005013513,
          "coherence": 0.027072253410487798,
          "order_parameter_abs": 0.0042920380350038815,
          "order_parameter_phase": -0.4178425552532792,
          "defect_density": 0.3125,
          "mean_winding_abs": 0.3125,
          "gradient_energy": 294.9567993137281,
          "potential_energy": 3.0236247661173894,
          "total_energy": 297.9804240798455,
          "stress_power": 0.0022615340784302137
        },
        {
          "sweep": 48,
          "temperature": 0.5256000000000001,
          "mean_amplitude": 0.15546559280932082,
          "coherence": 0.029139907711991923,
          "order_parameter_abs": 0.004530253026853724,
          "order_parameter_phase": -1.2222951413143628,
          "defect_density": 0.0,
          "mean_winding_abs": 0.0,
          "gradient_energy": 283.98420896641227,
          "potential_energy": 2.888796705479528,
          "total_energy": 286.8730056718918,
          "stress_power": 7.164646553117798e-12
        },
        {
          "sweep": 50,
          "temperature": 0.51,
          "mean_amplitude": 0.15378845944085123,
          "coherence": 0.020712735200898325,
          "order_parameter_abs": 0.0031853796373524437,
          "order_parameter_phase": -1.8033198830808712,
          "defect_density": 0.16666666666666666,
          "mean_winding_abs": 0.16666666666666666,
          "gradient_energy": 285.49114559968694,
          "potential_energy": 2.04653807723211,
          "total_energy": 287.5376836769191,
          "stress_power": 0.0011994634126374871
        },
        {
          "sweep": 52,
          "temperature": 0.4944,
          "mean_amplitude": 0.15046665974003412,
          "coherence": 0.03590097100407717,
          "order_parameter_abs": 0.005401899188407311,
          "order_parameter_phase": -0.4669791147259138,
          "defect_density": 0.0,
          "mean_winding_abs": 0.0,
          "gradient_energy": 263.280507857211,
          "potential_energy": 0.5028705331809306,
          "total_energy": 263.78337839039193,
          "stress_power": 5.7022232155679585e-12
        },
        {
          "sweep": 54,
          "temperature": 0.4788,
          "mean_amplitude": 0.14762546397582496,
          "coherence": 0.06044098078033676,
          "order_parameter_abs": 0.008922627830851133,
          "order_parameter_phase": -1.3277710641951201,
          "defect_density": 0.125,
          "mean_winding_abs": 0.125,
          "gradient_energy": 260.42195131524386,
          "potential_energy": -0.32735592142777037,
          "total_energy": 260.09459539381606,
          "stress_power": 0.0006990764299104692
        },
        {
          "sweep": 56,
          "temperature": 0.46319999999999995,
          "mean_amplitude": 0.1440879046796391,
          "coherence": 0.06497050307273046,
          "order_parameter_abs": 0.009361463653731786,
          "order_parameter_phase": -1.4482221505263575,
          "defect_density": 0.4,
          "mean_winding_abs": 0.4,
          "gradient_energy": 246.0839333850425,
          "potential_energy": -0.9867954525826432,
          "total_energy": 245.09713793245987,
          "stress_power": 0.002093877489760951
        },
        {
          "sweep": 58,
          "temperature": 0.44760000000000005,
          "mean_amplitude": 0.14288243331358097,
          "coherence": 0.05854483905815313,
          "order_parameter_abs": 0.008365029062580895,
          "order_parameter_phase": -0.82473855795887,
          "defect_density": 0.5,
          "mean_winding_abs": 0.5,
          "gradient_energy": 235.76177201940445,
          "potential_energy": -1.483828576370942,
          "total_energy": 234.2779434430335,
          "stress_power": 0.0024988476276343666
        },
        {
          "sweep": 60,
          "temperature": 0.43200000000000005,
          "mean_amplitude": 0.1435163844505586,
          "coherence": 0.059372164363426544,
          "order_parameter_abs": 0.008520878366443278,
          "order_parameter_phase": -0.9360078729906386,
          "defect_density": 0.3333333333333333,
          "mean_winding_abs": 0.3333333333333333,
          "gradient_energy": 234.19564085137912,
          "potential_energy": -2.137978418426357,
          "total_energy": 232.05766243295278,
          "stress_power": 0.001537786605135729
        },
        {
          "sweep": 62,
          "temperature": 0.4164,
          "mean_amplitude": 0.14218567559684356,
          "coherence": 0.061005984702973075,
          "order_parameter_abs": 0.00867417715044293,
          "order_parameter_phase": -0.5410079388244978,
          "defect_density": 0.0,
          "mean_winding_abs": 0.0,
          "gradient_energy": 230.42488776466368,
          "potential_energy": -2.7147396531638,
          "total_energy": 227.71014811149988,
          "stress_power": 4.201052953384891e-12
        },
        {
          "sweep": 64,
          "temperature": 0.4008,
          "mean_amplitude": 0.13646590611458764,
          "coherence": 0.04841488769415532,
          "order_parameter_abs": 0.006606981518618904,
          "order_parameter_phase": -0.9091118534972479,
          "defect_density": 0.0,
          "mean_winding_abs": 0.0,
          "gradient_energy": 211.6147243222103,
          "potential_energy": -2.966760154516956,
          "total_energy": 208.64796416769335,
          "stress_power": 3.6997972962003435e-12
        },
        {
          "sweep": 66,
          "temperature": 0.3852,
          "mean_amplitude": 0.12923795079793732,
          "coherence": 0.06966127373958342,
          "order_parameter_abs": 0.009002880268077924,
          "order_parameter_phase": -1.2224243055555575,
          "defect_density": 0.0,
          "mean_winding_abs": 0.0,
          "gradient_energy": 190.4883960478131,
          "potential_energy": -3.2283829571739053,
          "total_energy": 187.2600130906392,
          "stress_power": 3.1764744301082493e-12
        },
        {
          "sweep": 68,
          "temperature": 0.36959999999999993,
          "mean_amplitude": 0.1325603428028249,
          "coherence": 0.03237517331693925,
          "order_parameter_abs": 0.004291664073194337,
          "order_parameter_phase": -1.2469802258153475,
          "defect_density": 0.2,
          "mean_winding_abs": 0.2,
          "gradient_energy": 195.3834113301747,
          "potential_energy": -3.6551862660149745,
          "total_energy": 191.72822506415974,
          "stress_power": 0.0006381125696495771
        },
        {
          "sweep": 70,
          "temperature": 0.3540000000000001,
          "mean_amplitude": 0.12507598491250047,
          "coherence": 0.07448183904909947,
          "order_parameter_abs": 0.009315889377160453,
          "order_parameter_phase": -0.7081202828477347,
          "defect_density": 0.3333333333333333,
          "mean_winding_abs": 0.3333333333333333,
          "gradient_energy": 179.44282327715032,
          "potential_energy": -3.574446683295965,
          "total_energy": 175.86837659385435,
          "stress_power": 0.0012158170813926154
        },
        {
          "sweep": 72,
          "temperature": 0.33840000000000003,
          "mean_amplitude": 0.12353379381786649,
          "coherence": 0.07336762460289865,
          "order_parameter_abs": 0.00906338101060111,
          "order_parameter_phase": -0.8379525532144919,
          "defect_density": 0.0,
          "mean_winding_abs": 0.0,
          "gradient_energy": 175.45620097694285,
          "potential_energy": -4.153318102163296,
          "total_energy": 171.30288287477956,
          "stress_power": 2.914751508306271e-12
        },
        {
          "sweep": 74,
          "temperature": 0.3228,
          "mean_amplitude": 0.12241765859859627,
          "coherence": 0.05534273635461415,
          "order_parameter_abs": 0.0067749282049712764,
          "order_parameter_phase": -0.8340683960241657,
          "defect_density": 0.0,
          "mean_winding_abs": 0.0,
          "gradient_energy": 170.82107321765906,
          "potential_energy": -4.551301217520192,
          "total_energy": 166.26977200013886,
          "stress_power": 2.673764915199646e-12
        },
        {
          "sweep": 76,
          "temperature": 0.30720000000000003,
          "mean_amplitude": 0.12211231165793947,
          "coherence": 0.0727197843541737,
          "order_parameter_abs": 0.008879980970755008,
          "order_parameter_phase": -0.7538083381686848,
          "defect_density": 0.0,
          "mean_winding_abs": 0.0,
          "gradient_energy": 168.4769603993328,
          "potential_energy": -4.959461570678951,
          "total_energy": 163.51749882865386,
          "stress_power": 2.3685789453783103e-12
        },
        {
          "sweep": 78,
          "temperature": 0.29159999999999997,
          "mean_amplitude": 0.11826413267506979,
          "coherence": 0.03962138745542179,
          "order_parameter_abs": 0.004685789022798348,
          "order_parameter_phase": -0.866548054009532,
          "defect_density": 0.0,
          "mean_winding_abs": 0.0,
          "gradient_energy": 159.83467880050608,
          "potential_energy": -5.055915575365063,
          "total_energy": 154.778763225141,
          "stress_power": 2.3479816916196996e-12
        },
        {
          "sweep": 80,
          "temperature": 0.2759999999999999,
          "mean_amplitude": 0.11464289787232625,
          "coherence": 0.039902610168053784,
          "order_parameter_abs": 0.004574550862335437,
          "order_parameter_phase": -0.48605972375024575,
          "defect_density": 0.0,
          "mean_winding_abs": 0.0,
          "gradient_energy": 145.96000133632376,
          "potential_energy": -5.159772208675762,
          "total_energy": 140.80022912764798,
          "stress_power": 1.7861512331267938e-12
        },
        {
          "sweep": 82,
          "temperature": 0.2604000000000001,
          "mean_amplitude": 0.1099485689593521,
          "coherence": 0.03218733972156055,
          "order_parameter_abs": 0.003538951940994093,
          "order_parameter_phase": -1.3531788658760944,
          "defect_density": 0.0,
          "mean_winding_abs": 0.0,
          "gradient_energy": 142.3803984173256,
          "potential_energy": -5.238532846068555,
          "total_energy": 137.14186557125706,
          "stress_power": 1.608435325134343e-12
        },
        {
          "sweep": 84,
          "temperature": 0.24480000000000002,
          "mean_amplitude": 0.11036224277404091,
          "coherence": 0.04157320077137835,
          "order_parameter_abs": 0.004588111676424802,
          "order_parameter_phase": -1.5641247822150566,
          "defect_density": 1.0,
          "mean_winding_abs": 1.0,
          "gradient_energy": 140.29372223884798,
          "potential_energy": -5.559215473922573,
          "total_energy": 134.7345067649254,
          "stress_power": 0.0015060838323763574
        },
        {
          "sweep": 86,
          "temperature": 0.22919999999999996,
          "mean_amplitude": 0.10600080023761813,
          "coherence": 0.05813161769251909,
          "order_parameter_abs": 0.006161997994514303,
          "order_parameter_phase": -2.1622451830505205,
          "defect_density": 0.0,
          "mean_winding_abs": 0.0,
          "gradient_energy": 132.02917894683463,
          "potential_energy": -5.48323682779521,
          "total_energy": 126.54594211903942,
          "stress_power": 1.4216216526060033e-12
        },
        {
          "sweep": 88,
          "temperature": 0.2136,
          "mean_amplitude": 0.10617660420655176,
          "coherence": 0.07621596652736018,
          "order_parameter_abs": 0.008092352512195318,
          "order_parameter_phase": -1.6905247877541933,
          "defect_density": 0.0,
          "mean_winding_abs": 0.0,
          "gradient_energy": 130.7198651926169,
          "potential_energy": -5.761972088579338,
          "total_energy": 124.95789310403757,
          "stress_power": 1.3867774305064416e-12
        },
        {
          "sweep": 90,
          "temperature": 0.19799999999999995,
          "mean_amplitude": 0.10061575721747659,
          "coherence": 0.056044214414912065,
          "order_parameter_abs": 0.005638931071014994,
          "order_parameter_phase": -2.125351490477253,
          "defect_density": 0.0,
          "mean_winding_abs": 0.0,
          "gradient_energy": 117.93021513946255,
          "potential_energy": -5.39962388110166,
          "total_energy": 112.53059125836089,
          "stress_power": 1.1339919494598622e-12
        },
        {
          "sweep": 92,
          "temperature": 0.1824,
          "mean_amplitude": 0.09785528273047311,
          "coherence": 0.056293603034654666,
          "order_parameter_abs": 0.005508626440873151,
          "order_parameter_phase": -1.4517901311614878,
          "defect_density": 0.0,
          "mean_winding_abs": 0.0,
          "gradient_energy": 112.11635651396018,
          "potential_energy": -5.4847579595299925,
          "total_energy": 106.6315985544302,
          "stress_power": 1.0499564822114156e-12
        },
        {
          "sweep": 94,
          "temperature": 0.16680000000000006,
          "mean_amplitude": 0.09158134343654903,
          "coherence": 0.0621403182137453,
          "order_parameter_abs": 0.005690893823589451,
          "order_parameter_phase": -1.542729392752868,
          "defect_density": 0.0,
          "mean_winding_abs": 0.0,
          "gradient_energy": 96.61509038030695,
          "potential_energy": -5.116089138428532,
          "total_energy": 91.49900124187842,
          "stress_power": 7.918089889506405e-13
        },
        {
          "sweep": 96,
          "temperature": 0.1512,
          "mean_amplitude": 0.08769115804356699,
          "coherence": 0.042533423763268755,
          "order_parameter_abs": 0.003729805185358808,
          "order_parameter_phase": -1.0420540023854006,
          "defect_density": 0.0,
          "mean_winding_abs": 0.0,
          "gradient_energy": 86.85295100491935,
          "potential_energy": -4.877681014995054,
          "total_energy": 81.9752699899243,
          "stress_power": 6.124235634446449e-13
        },
        {
          "sweep": 98,
          "temperature": 0.13560000000000005,
          "mean_amplitude": 0.08357510446832969,
          "coherence": 0.04494984515294853,
          "order_parameter_abs": 0.0037566880044929162,
          "order_parameter_phase": -1.4067612614664213,
          "defect_density": 0.0,
          "mean_winding_abs": 0.0,
          "gradient_energy": 78.74710771596453,
          "potential_energy": -4.54145828756061,
          "total_energy": 74.20564942840392,
          "stress_power": 4.834086087139508e-13
        },
        {
          "sweep": 100,
          "temperature": 0.12,
          "mean_amplitude": 0.08223391495443538,
          "coherence": 0.03326539110772003,
          "order_parameter_abs": 0.00273554334327828,
          "order_parameter_phase": -0.8387291309029076,
          "defect_density": 0.5,
          "mean_winding_abs": 0.5,
          "gradient_energy": 76.7530030400817,
          "potential_energy": -4.565544922352164,
          "total_energy": 72.18745811772953,
          "stress_power": 0.00021496502733487545
        },
        {
          "sweep": 102,
          "temperature": 0.12,
          "mean_amplitude": 0.07804397625686949,
          "coherence": 0.020118853947640628,
          "order_parameter_abs": 0.0015701553598050902,
          "order_parameter_phase": -1.5887854577939173,
          "defect_density": 0.0,
          "mean_winding_abs": 0.0,
          "gradient_energy": 69.91203460109648,
          "potential_energy": -4.184370997138494,
          "total_energy": 65.72766360395798,
          "stress_power": 3.608602135764824e-13
        },
        {
          "sweep": 104,
          "temperature": 0.12,
          "mean_amplitude": 0.07668616270167489,
          "coherence": 0.00932757347441105,
          "order_parameter_abs": 0.0007152958170705128,
          "order_parameter_phase": 2.0899445441684925,
          "defect_density": 0.0,
          "mean_winding_abs": 0.0,
          "gradient_energy": 68.62419875782444,
          "potential_energy": -4.101602030973944,
          "total_energy": 64.5225967268505,
          "stress_power": 3.8557905666630936e-13
        },
        {
          "sweep": 106,
          "temperature": 0.12,
          "mean_amplitude": 0.07434973676951512,
          "coherence": 0.023706228342646067,
          "order_parameter_abs": 0.0017625518370737538,
          "order_parameter_phase": 1.2113887346330592,
          "defect_density": 0.0,
          "mean_winding_abs": 0.0,
          "gradient_energy": 65.12222306701437,
          "potential_energy": -3.8212190328820426,
          "total_energy": 61.30100403413233,
          "stress_power": 3.526457910631178e-13
        },
        {
          "sweep": 108,
          "temperature": 0.12,
          "mean_amplitude": 0.07372481297472289,
          "coherence": 0.010803550556432368,
          "order_parameter_abs": 0.0007964897442359396,
          "order_parameter_phase": -2.422819399893888,
          "defect_density": 0.0,
          "mean_winding_abs": 0.0,
          "gradient_energy": 63.39718479837142,
          "potential_energy": -3.8425398431038826,
          "total_energy": 59.554644955267534,
          "stress_power": 3.437239129418643e-13
        },
        {
          "sweep": 110,
          "temperature": 0.12,
          "mean_amplitude": 0.07221764980704316,
          "coherence": 0.042351678926005734,
          "order_parameter_abs": 0.003058538717418612,
          "order_parameter_phase": -0.46431552808965915,
          "defect_density": 0.0,
          "mean_winding_abs": 0.0,
          "gradient_energy": 60.58278076702084,
          "potential_energy": -3.6468671083933626,
          "total_energy": 56.93591365862748,
          "stress_power": 2.854598393920644e-13
        },
        {
          "sweep": 112,
          "temperature": 0.12,
          "mean_amplitude": 0.0722114711573326,
          "coherence": 0.05331112091727293,
          "order_parameter_abs": 0.003849674470482725,
          "order_parameter_phase": -0.1832688038020711,
          "defect_density": 0.0,
          "mean_winding_abs": 0.0,
          "gradient_energy": 62.71197793404575,
          "potential_energy": -3.6494319877776045,
          "total_energy": 59.062545946268145,
          "stress_power": 3.328251532582485e-13
        },
        {
          "sweep": 114,
          "temperature": 0.12,
          "mean_amplitude": 0.07262503366248282,
          "coherence": 0.06314975257682792,
          "order_parameter_abs": 0.004586252906669589,
          "order_parameter_phase": 0.2347524023312768,
          "defect_density": 0.0,
          "mean_winding_abs": 0.0,
          "gradient_energy": 61.60282644614391,
          "potential_energy": -3.6889001278050446,
          "total_energy": 57.913926318338866,
          "stress_power": 2.9924304157102783e-13
        },
        {
          "sweep": 116,
          "temperature": 0.12,
          "mean_amplitude": 0.07363598888465836,
          "coherence": 0.023370249356351604,
          "order_parameter_abs": 0.0017208914218360008,
          "order_parameter_phase": -0.14085601141111512,
          "defect_density": 0.0,
          "mean_winding_abs": 0.0,
          "gradient_energy": 63.348605618703466,
          "potential_energy": -3.708951616178808,
          "total_energy": 59.63965400252466,
          "stress_power": 3.20559991353226e-13
        },
        {
          "sweep": 118,
          "temperature": 0.12,
          "mean_amplitude": 0.07730732505878893,
          "coherence": 0.03471201154305852,
          "order_parameter_abs": 0.002683492759803659,
          "order_parameter_phase": -0.876011180929917,
          "defect_density": 0.0,
          "mean_winding_abs": 0.0,
          "gradient_energy": 67.33432442632702,
          "potential_energy": -4.01388444266523,
          "total_energy": 63.320439983661785,
          "stress_power": 3.5417199341875933e-13
        },
        {
          "sweep": 120,
          "temperature": 0.12,
          "mean_amplitude": 0.07534492872057325,
          "coherence": 0.037899355281352264,
          "order_parameter_abs": 0.0028555242222291673,
          "order_parameter_phase": -0.9704280357488281,
          "defect_density": 0.0,
          "mean_winding_abs": 0.0,
          "gradient_energy": 65.41230367049099,
          "potential_energy": -3.9695132925519587,
          "total_energy": 61.442790377939026,
          "stress_power": 3.910641655887712e-13
        }
      ],
      "spectrum": [
        {
          "frequency": 0.00819672131147541,
          "power": 7.970200075576313e-06
        },
        {
          "frequency": 0.01639344262295082,
          "power": 2.165949945013938e-07
        },
        {
          "frequency": 0.02459016393442623,
          "power": 3.3429640163562876e-07
        },
        {
          "frequency": 0.03278688524590164,
          "power": 2.626252300550692e-07
        },
        {
          "frequency": 0.04098360655737705,
          "power": 7.286554443276593e-07
        },
        {
          "frequency": 0.04918032786885246,
          "power": 1.198322335622983e-07
        },
        {
          "frequency": 0.05737704918032787,
          "power": 3.365624113560994e-07
        },
        {
          "frequency": 0.06557377049180328,
          "power": 1.660346091216654e-07
        },
        {
          "frequency": 0.07377049180327869,
          "power": 1.781516508205552e-06
        },
        {
          "frequency": 0.0819672131147541,
          "power": 1.2166710913805107e-06
        },
        {
          "frequency": 0.09016393442622951,
          "power": 4.103044442913078e-07
        },
        {
          "frequency": 0.09836065573770492,
          "power": 8.190856182821005e-08
        },
        {
          "frequency": 0.10655737704918034,
          "power": 3.0754190852761216e-07
        },
        {
          "frequency": 0.11475409836065574,
          "power": 4.2403921257871846e-07
        },
        {
          "frequency": 0.12295081967213116,
          "power": 3.100403343571633e-07
        },
        {
          "frequency": 0.13114754098360656,
          "power": 1.3373568513532479e-07
        },
        {
          "frequency": 0.13934426229508198,
          "power": 4.766895723566313e-08
        },
        {
          "frequency": 0.14754098360655737,
          "power": 3.2684089096785514e-07
        },
        {
          "frequency": 0.1557377049180328,
          "power": 3.4187979787724475e-07
        },
        {
          "frequency": 0.1639344262295082,
          "power": 7.582672981118627e-08
        },
        {
          "frequency": 0.1721311475409836,
          "power": 2.155215857569349e-07
        },
        {
          "frequency": 0.18032786885245902,
          "power": 5.588794305299756e-07
        },
        {
          "frequency": 0.18852459016393444,
          "power": 3.8825096370065005e-08
        },
        {
          "frequency": 0.19672131147540983,
          "power": 7.863738320307381e-08
        },
        {
          "frequency": 0.20491803278688525,
          "power": 3.347135790134628e-07
        },
        {
          "frequency": 0.21311475409836067,
          "power": 2.7644913128772776e-07
        },
        {
          "frequency": 0.2213114754098361,
          "power": 2.4484711840183947e-07
        },
        {
          "frequency": 0.22950819672131148,
          "power": 2.5763156767570124e-07
        },
        {
          "frequency": 0.2377049180327869,
          "power": 6.83412338844813e-08
        },
        {
          "frequency": 0.24590163934426232,
          "power": 4.133519250875968e-07
        }
      ]
    }
  ]
}